pyoctal/__init__.py
pyoctal/instruments/__init__.py
pyoctal/instruments/agilent816xB.py
pyoctal/instruments/agilentDSO8000.py
pyoctal/instruments/agilentE3640.py
pyoctal/instruments/agilentN777xC.py
pyoctal/instruments/ametekDSP72XX.py
pyoctal/instruments/arroyo6301.py
pyoctal/instruments/base.py
pyoctal/instruments/daylightQCL.py
pyoctal/instruments/exfoXTA50.py
pyoctal/instruments/fiberlabsAMP.py
pyoctal/instruments/keithley2400.py
pyoctal/instruments/keithley6487.py
pyoctal/instruments/keysight86100D.py
pyoctal/instruments/keysightE8257D.py
pyoctal/instruments/keysightPAS.py
pyoctal/instruments/tektronixScope.py
pyoctal/instruments/thorlabsAPT.py
pyoctal/instruments/thorlabsITC40XX.py
pyoctal/instruments/thorlabsPM100.py
pyoctal/instruments/ttiTGF3162.py
pyoctal/instruments/xpow.py
pyoctal/utils/__init__.py
pyoctal/utils/error.py
pyoctal/utils/file_operations.py
pyoctal/utils/formatter.py
pyoctal/utils/util.py
pyoctal-0.0.7.dist-info/LICENSE.txt
pyoctal-0.0.7.dist-info/METADATA
pyoctal-0.0.7.dist-info/WHEEL
pyoctal-0.0.7.dist-info/top_level.txt
pyoctal-0.0.7.dist-info/RECORD
