Metadata-Version: 2.2
Name: pyoctal
Version: 0.0.7
Summary: Optical chip automated testing library equipped with a wide range of instruments interface.
Author-email: Tzu-Yun Chang <tyc1g20@soton.ac.uk>
Project-URL: Repository, https://github.com/christina-chang-tw/PyOctal
Classifier: Programming Language :: Python :: 3
Classifier: License :: OSI Approved :: GNU General Public License v3 (GPLv3)
Classifier: Operating System :: Microsoft :: Windows
Classifier: Development Status :: 2 - Pre-Alpha
Requires-Python: >=3.6
License-File: LICENSE.txt
Provides-Extra: tests
Requires-Dist: pytest>=7.1.2; extra == "tests"
Requires-Dist: pywin32; platform_system != "Windows" and extra == "tests"
Requires-Dist: pyvisa-sim; extra == "tests"
